cachedir_tag/__init__.py
cachedir_tag-0.0.3.dist-info/METADATA
cachedir_tag-0.0.3.dist-info/WHEEL
cachedir_tag-0.0.3.dist-info/top_level.txt
cachedir_tag-0.0.3.dist-info/RECORD
