Metadata-Version: 2.1
Name: cachedir-tag
Version: 0.0.3
Summary: Handle CACHEDIR.TAG files, indicating directories that contain cached content
Home-page: https://github.com/moreati/python-cachedir-tag
Author: Alex Willmer
Author-email: alex@moreati.org.uk
License: UNKNOWN
Keywords: cache,cachedir,cachedirtag
Platform: UNKNOWN
Classifier: Development Status :: 3 - Alpha
Classifier: License :: OSI Approved :: MIT License
Classifier: Operating System :: OS Independent
Classifier: Programming Language :: Python
Requires-Python: !=3.0.*,!=3.1.*,!=3.2.*,!=3.3.*,!=3.4.*,!=3.5.*,>=2.7
Requires-Dist: pathlib ; python_version <= "2.7"
